dataparser/__init__.py
dataparser/parser.py
dataparser-0.0.2.dist-info/LICENSE
dataparser-0.0.2.dist-info/METADATA
dataparser-0.0.2.dist-info/WHEEL
dataparser-0.0.2.dist-info/top_level.txt
dataparser-0.0.2.dist-info/RECORD
